[
    {
        "name": "MARQUE PLACE COEUR 6 PIECES",
        "type": "simple",
        "regular_price": "1,40 €",
        "description": [
            "<strong>Matiere</strong> : PAPIER",
            "<strong>Dimensions produit</strong> : 6.5x6CM",
            "<strong>Colisage</strong> : 12",
            "<strong>Produits interieur (pcs)</strong> : 6 PIECES",
            "<strong>Poids du produit (kg)</strong> : 0.02"
        ],
        "image": "https://www.fetez-moi.net/394452-large_default/2350BL-marque-place-coeur-6-pieces.jpg",
        "images": [
            "https://www.fetez-moi.net/394452-thickbox_default/2350BL-marque-place-coeur-6-pieces.jpg",
            "https://www.fetez-moi.net/394452/2350BL-marque-place-coeur-6-pieces.jpg"
        ]
    },
    {
        "name": "ETIQUETTE X10 PCS",
        "type": "simple",
        "regular_price": "0,95 €",
        "description": [
            "<strong>Dimensions colis (cm)</strong> : 19 x 18 x 13",
            "<strong>Matiere</strong> : carton",
            "<strong>Dimensions produit</strong> : 4x4.5cm",
            "<strong>Colisage</strong> : 24",
            "<strong>Produits interieur (pcs)</strong> : sachet de  12",
            "<strong>Poids du produit (kg)</strong> : 0.017",
            "<strong>Poids du colis (kg)</strong> : 0.408"
        ],
        "image": "https://www.fetez-moi.net/img/p/fr-default-large_default.jpg",
        "images": []
    },
    {
        "name": "ETIQUETTE COEUR 12 pcs",
        "type": "simple",
        "regular_price": "0,95 €",
        "description": [
            "<strong>Dimensions colis (cm)</strong> : 19 x 18 x 13",
            "<strong>Matiere</strong> : carton",
            "<strong>Dimensions produit</strong> : 2.5x4.5cm",
            "<strong>Colisage</strong> : 24",
            "<strong>Produits interieur (pcs)</strong> : sachet de  12",
            "<strong>Poids du produit (kg)</strong> : 0.017",
            "<strong>Poids du colis (kg)</strong> : 0.408"
        ],
        "image": "https://www.fetez-moi.net/394280-large_default/792BE-etiquette-coeur-12-pcs.jpg",
        "images": [
            "https://www.fetez-moi.net/394280-thickbox_default/792BE-etiquette-coeur-12-pcs.jpg",
            "https://www.fetez-moi.net/394280/792BE-etiquette-coeur-12-pcs.jpg",
            "https://www.fetez-moi.net/397754-thickbox_default/792BE-etiquette-coeur-12-pcs.jpg",
            "https://www.fetez-moi.net/397754/792BE-etiquette-coeur-12-pcs.jpg",
            "https://www.fetez-moi.net/395903-thickbox_default/792BE-etiquette-coeur-12-pcs.jpg",
            "https://www.fetez-moi.net/395903/792BE-etiquette-coeur-12-pcs.jpg"
        ]
    },
    {
        "name": "ETIQUETTE COEUR 12 pcs",
        "type": "simple",
        "regular_price": "0,95 €",
        "description": [
            "<strong>Dimensions colis (cm)</strong> : 19  x 18 x 13",
            "<strong>Matiere</strong> : carton",
            "<strong>Dimensions produit</strong> : 4x4,5cm",
            "<strong>Colisage</strong> : 24",
            "<strong>Produits interieur (pcs)</strong> : sachet de  12",
            "<strong>Poids du produit (kg)</strong> : 0,017",
            "<strong>Poids du colis (kg)</strong> : 0,408"
        ],
        "image": "https://www.fetez-moi.net/391323-large_default/792BL-etiquette-coeur-12-pcs.jpg",
        "images": [
            "https://www.fetez-moi.net/391323-thickbox_default/792BL-etiquette-coeur-12-pcs.jpg",
            "https://www.fetez-moi.net/391323/792BL-etiquette-coeur-12-pcs.jpg",
            "https://www.fetez-moi.net/397785-thickbox_default/792BL-etiquette-coeur-12-pcs.jpg",
            "https://www.fetez-moi.net/397785/792BL-etiquette-coeur-12-pcs.jpg",
            "https://www.fetez-moi.net/395905-thickbox_default/792BL-etiquette-coeur-12-pcs.jpg",
            "https://www.fetez-moi.net/395905/792BL-etiquette-coeur-12-pcs.jpg",
            "https://www.fetez-moi.net/397758-thickbox_default/792BL-etiquette-coeur-12-pcs.jpg",
            "https://www.fetez-moi.net/397758/792BL-etiquette-coeur-12-pcs.jpg"
        ]
    },
    {
        "name": "ETIQUETTE COEUR 12 pcs",
        "type": "simple",
        "regular_price": "0,95 €",
        "description": [
            "<strong>Dimensions colis (cm)</strong> : 19 x 18 x 13",
            "<strong>Matiere</strong> : carton",
            "<strong>Dimensions produit</strong> : 2.5x4.5cm",
            "<strong>Colisage</strong> : 24",
            "<strong>Produits interieur (pcs)</strong> : sachet de  12",
            "<strong>Poids du produit (kg)</strong> : 0.017",
            "<strong>Poids du colis (kg)</strong> : 0.408",
            "<strong>DATE DE REAPPROVISIONNEMENT</strong> :  "
        ],
        "image": "https://www.fetez-moi.net/394493-large_default/792RO-etiquette-coeur-12-pcs.jpg",
        "images": [
            "https://www.fetez-moi.net/394493-thickbox_default/792RO-etiquette-coeur-12-pcs.jpg",
            "https://www.fetez-moi.net/394493/792RO-etiquette-coeur-12-pcs.jpg",
            "https://www.fetez-moi.net/397755-thickbox_default/792RO-etiquette-coeur-12-pcs.jpg",
            "https://www.fetez-moi.net/397755/792RO-etiquette-coeur-12-pcs.jpg",
            "https://www.fetez-moi.net/395902-thickbox_default/792RO-etiquette-coeur-12-pcs.jpg",
            "https://www.fetez-moi.net/395902/792RO-etiquette-coeur-12-pcs.jpg"
        ]
    },
    {
        "name": "ETIQUETTE RECTANGLE KRAFT 12 pcs",
        "type": "simple",
        "regular_price": "0,80 €",
        "description": [
            "<strong>Dimensions colis (cm)</strong> : 19 X 13 X 12",
            "<strong>Matiere</strong> : carton",
            "<strong>Dimensions produit</strong> : 4x4.5cm",
            "<strong>Colisage</strong> : 24",
            "<strong>Produits interieur (pcs)</strong> : 12",
            "<strong>Poids du produit (kg)</strong> : 0.011",
            "<strong>Poids du colis (kg)</strong> : 0.294"
        ],
        "image": "https://www.fetez-moi.net/393529-large_default/793NA-etiquette-rectangle-kraft-12-pcs.jpg",
        "images": [
            "https://www.fetez-moi.net/393529-thickbox_default/793NA-etiquette-rectangle-kraft-12-pcs.jpg",
            "https://www.fetez-moi.net/393529/793NA-etiquette-rectangle-kraft-12-pcs.jpg",
            "https://www.fetez-moi.net/397783-thickbox_default/793NA-etiquette-rectangle-kraft-12-pcs.jpg",
            "https://www.fetez-moi.net/397783/793NA-etiquette-rectangle-kraft-12-pcs.jpg",
            "https://www.fetez-moi.net/395993-thickbox_default/793NA-etiquette-rectangle-kraft-12-pcs.jpg",
            "https://www.fetez-moi.net/395993/793NA-etiquette-rectangle-kraft-12-pcs.jpg",
            "https://www.fetez-moi.net/397766-thickbox_default/793NA-etiquette-rectangle-kraft-12-pcs.jpg",
            "https://www.fetez-moi.net/397766/793NA-etiquette-rectangle-kraft-12-pcs.jpg"
        ]
    },
    {
        "name": "ETIQUETTE RECTANGLE 12 pcs",
        "type": "simple",
        "regular_price": "0,80 €",
        "description": [
            "<strong>Dimensions colis (cm)</strong> : 19 X 13 X 12",
            "<strong>Matiere</strong> : carton",
            "<strong>Dimensions produit</strong> : 4x4.5cm",
            "<strong>Colisage</strong> : 24",
            "<strong>Produits interieur (pcs)</strong> : 12",
            "<strong>Poids du produit (kg)</strong> : 0.011",
            "<strong>Poids du colis (kg)</strong> : 0.294"
        ],
        "image": "https://www.fetez-moi.net/393588-large_default/793RO-etiquette-rectangle-12-pcs.jpg",
        "images": [
            "https://www.fetez-moi.net/393588-thickbox_default/793RO-etiquette-rectangle-12-pcs.jpg",
            "https://www.fetez-moi.net/393588/793RO-etiquette-rectangle-12-pcs.jpg",
            "https://www.fetez-moi.net/397762-thickbox_default/793RO-etiquette-rectangle-12-pcs.jpg",
            "https://www.fetez-moi.net/397762/793RO-etiquette-rectangle-12-pcs.jpg",
            "https://www.fetez-moi.net/395989-thickbox_default/793RO-etiquette-rectangle-12-pcs.jpg",
            "https://www.fetez-moi.net/395989/793RO-etiquette-rectangle-12-pcs.jpg"
        ]
    },
    {
        "name": "ETIQUETTE RECTANGLE 12 pcs",
        "type": "simple",
        "regular_price": "0,80 €",
        "description": [
            "<strong>Dimensions colis (cm)</strong> : 19 X 13 X 12",
            "<strong>Matiere</strong> : carton",
            "<strong>Dimensions produit</strong> : 4x4.5cm",
            "<strong>Colisage</strong> : 24",
            "<strong>Produits interieur (pcs)</strong> : 12",
            "<strong>Poids du produit (kg)</strong> : 0.011",
            "<strong>Poids du colis (kg)</strong> : 0.294"
        ],
        "image": "https://www.fetez-moi.net/394279-large_default/793BE-etiquette-rectangle-12-pcs.jpg",
        "images": [
            "https://www.fetez-moi.net/394279-thickbox_default/793BE-etiquette-rectangle-12-pcs.jpg",
            "https://www.fetez-moi.net/394279/793BE-etiquette-rectangle-12-pcs.jpg",
            "https://www.fetez-moi.net/397763-thickbox_default/793BE-etiquette-rectangle-12-pcs.jpg",
            "https://www.fetez-moi.net/397763/793BE-etiquette-rectangle-12-pcs.jpg",
            "https://www.fetez-moi.net/395991-thickbox_default/793BE-etiquette-rectangle-12-pcs.jpg",
            "https://www.fetez-moi.net/395991/793BE-etiquette-rectangle-12-pcs.jpg"
        ]
    },
    {
        "name": "ETIQUETTE JUST MARRIED 10 PIECES",
        "type": "simple",
        "regular_price": "1,17 €",
        "description": [
            "<strong>Matiere</strong> : PAPIER",
            "<strong>Dimensions produit</strong> : 10x5CM",
            "<strong>Colisage</strong> : 24",
            "<strong>Produits interieur (pcs)</strong> : sachet de 12",
            "<strong>Poids du produit (kg)</strong> : 0.02"
        ],
        "image": "https://www.fetez-moi.net/397895-large_default/2320BL-etiquette-just-married-10-pieces.jpg",
        "images": [
            "https://www.fetez-moi.net/397895-thickbox_default/2320BL-etiquette-just-married-10-pieces.jpg",
            "https://www.fetez-moi.net/397895/2320BL-etiquette-just-married-10-pieces.jpg",
            "https://www.fetez-moi.net/395376-thickbox_default/2320BL-etiquette-just-married-10-pieces.jpg",
            "https://www.fetez-moi.net/395376/2320BL-etiquette-just-married-10-pieces.jpg",
            "https://www.fetez-moi.net/397749-thickbox_default/2320BL-etiquette-just-married-10-pieces.jpg",
            "https://www.fetez-moi.net/397749/2320BL-etiquette-just-married-10-pieces.jpg",
            "https://www.fetez-moi.net/395341-thickbox_default/2320BL-etiquette-just-married-10-pieces.jpg",
            "https://www.fetez-moi.net/395341/2320BL-etiquette-just-married-10-pieces.jpg",
            "https://www.fetez-moi.net/397750-thickbox_default/2320BL-etiquette-just-married-10-pieces.jpg",
            "https://www.fetez-moi.net/397750/2320BL-etiquette-just-married-10-pieces.jpg"
        ]
    },
    {
        "name": "ETIQUETTE COEUR KRAFT 12 pcs",
        "type": "simple",
        "regular_price": "0,95 €",
        "description": [
            "<strong>Dimensions colis (cm)</strong> : 19 x 18 x 13",
            "<strong>Matiere</strong> : carton",
            "<strong>Dimensions produit</strong> : 2.5x4.5cm",
            "<strong>Colisage</strong> : 24",
            "<strong>Produits interieur (pcs)</strong> : sachet de  12",
            "<strong>Poids du produit (kg)</strong> : 0.017",
            "<strong>Poids du colis (kg)</strong> : 0.408"
        ],
        "image": "https://www.fetez-moi.net/393527-large_default/792NA-etiquette-coeur-kraft-12-pcs.jpg",
        "images": [
            "https://www.fetez-moi.net/393527-thickbox_default/792NA-etiquette-coeur-kraft-12-pcs.jpg",
            "https://www.fetez-moi.net/393527/792NA-etiquette-coeur-kraft-12-pcs.jpg",
            "https://www.fetez-moi.net/397914-thickbox_default/792NA-etiquette-coeur-kraft-12-pcs.jpg",
            "https://www.fetez-moi.net/397914/792NA-etiquette-coeur-kraft-12-pcs.jpg",
            "https://www.fetez-moi.net/397767-thickbox_default/792NA-etiquette-coeur-kraft-12-pcs.jpg",
            "https://www.fetez-moi.net/397767/792NA-etiquette-coeur-kraft-12-pcs.jpg",
            "https://www.fetez-moi.net/394963-thickbox_default/792NA-etiquette-coeur-kraft-12-pcs.jpg",
            "https://www.fetez-moi.net/394963/792NA-etiquette-coeur-kraft-12-pcs.jpg",
            "https://www.fetez-moi.net/395908-thickbox_default/792NA-etiquette-coeur-kraft-12-pcs.jpg",
            "https://www.fetez-moi.net/395908/792NA-etiquette-coeur-kraft-12-pcs.jpg",
            "https://www.fetez-moi.net/397913-thickbox_default/792NA-etiquette-coeur-kraft-12-pcs.jpg",
            "https://www.fetez-moi.net/397913/792NA-etiquette-coeur-kraft-12-pcs.jpg"
        ]
    },
    {
        "name": "ETIQUETTE RECTANGLE 12 pcs",
        "type": "simple",
        "regular_price": "0,80 €",
        "description": [
            "<strong>Dimensions colis (cm)</strong> : 19 X 13 X 12",
            "<strong>Matiere</strong> : carton",
            "<strong>Dimensions produit</strong> : 2.5x4.5cm",
            "<strong>Colisage</strong> : 24",
            "<strong>Produits interieur (pcs)</strong> : 12",
            "<strong>Poids du produit (kg)</strong> : 0.011",
            "<strong>Poids du colis (kg)</strong> : 0.294"
        ],
        "image": "https://www.fetez-moi.net/391347-large_default/793FU-etiquette-rectangle-12-pcs.jpg",
        "images": [
            "https://www.fetez-moi.net/391347-thickbox_default/793FU-etiquette-rectangle-12-pcs.jpg",
            "https://www.fetez-moi.net/391347/793FU-etiquette-rectangle-12-pcs.jpg",
            "https://www.fetez-moi.net/395988-thickbox_default/793FU-etiquette-rectangle-12-pcs.jpg",
            "https://www.fetez-moi.net/395988/793FU-etiquette-rectangle-12-pcs.jpg",
            "https://www.fetez-moi.net/397764-thickbox_default/793FU-etiquette-rectangle-12-pcs.jpg",
            "https://www.fetez-moi.net/397764/793FU-etiquette-rectangle-12-pcs.jpg",
            "https://www.fetez-moi.net/391350-thickbox_default/793FU-etiquette-rectangle-12-pcs.jpg",
            "https://www.fetez-moi.net/391350/793FU-etiquette-rectangle-12-pcs.jpg",
            "https://www.fetez-moi.net/391351-thickbox_default/793FU-etiquette-rectangle-12-pcs.jpg",
            "https://www.fetez-moi.net/391351/793FU-etiquette-rectangle-12-pcs.jpg",
            "https://www.fetez-moi.net/391353-thickbox_default/793FU-etiquette-rectangle-12-pcs.jpg",
            "https://www.fetez-moi.net/391353/793FU-etiquette-rectangle-12-pcs.jpg"
        ]
    },
    {
        "name": "ETIQUETTE RECTANGLE 12 pcs",
        "type": "simple",
        "regular_price": "0,80 €",
        "description": [
            "<strong>Dimensions colis (cm)</strong> : 19 X 13 X 12",
            "<strong>Matiere</strong> : papier",
            "<strong>Dimensions produit</strong> : 2,5x4,5cm",
            "<strong>Colisage</strong> : 24",
            "<strong>Produits interieur (pcs)</strong> : 12",
            "<strong>Poids du produit (kg)</strong> : 0,011",
            "<strong>Poids du colis (kg)</strong> : 0,294"
        ],
        "image": "https://www.fetez-moi.net/391338-large_default/793BL-etiquette-rectangle-12-pcs.jpg",
        "images": [
            "https://www.fetez-moi.net/391338-thickbox_default/793BL-etiquette-rectangle-12-pcs.jpg",
            "https://www.fetez-moi.net/391338/793BL-etiquette-rectangle-12-pcs.jpg",
            "https://www.fetez-moi.net/397760-thickbox_default/793BL-etiquette-rectangle-12-pcs.jpg",
            "https://www.fetez-moi.net/397760/793BL-etiquette-rectangle-12-pcs.jpg",
            "https://www.fetez-moi.net/395990-thickbox_default/793BL-etiquette-rectangle-12-pcs.jpg",
            "https://www.fetez-moi.net/395990/793BL-etiquette-rectangle-12-pcs.jpg",
            "https://www.fetez-moi.net/391339-thickbox_default/793BL-etiquette-rectangle-12-pcs.jpg",
            "https://www.fetez-moi.net/391339/793BL-etiquette-rectangle-12-pcs.jpg",
            "https://www.fetez-moi.net/391340-thickbox_default/793BL-etiquette-rectangle-12-pcs.jpg",
            "https://www.fetez-moi.net/391340/793BL-etiquette-rectangle-12-pcs.jpg",
            "https://www.fetez-moi.net/391341-thickbox_default/793BL-etiquette-rectangle-12-pcs.jpg",
            "https://www.fetez-moi.net/391341/793BL-etiquette-rectangle-12-pcs.jpg"
        ]
    },
    {
        "name": "ETIQUETTE COEUR 12 pcs",
        "type": "simple",
        "regular_price": "0,95 €",
        "description": [
            "<strong>Dimensions colis (cm)</strong> : 19X 18 X 13",
            "<strong>Matiere</strong> : carton",
            "<strong>Dimensions produit</strong> : 4 x 4.5 cm",
            "<strong>Colisage</strong> : 24",
            "<strong>Produits interieur (pcs)</strong> : sachet de 12",
            "<strong>Poids du produit (kg)</strong> : 0.017",
            "<strong>Poids du colis (kg)</strong> : 0.408"
        ],
        "image": "https://www.fetez-moi.net/391321-large_default/792AR-etiquette-coeur-12-pcs.jpg",
        "images": [
            "https://www.fetez-moi.net/391321-thickbox_default/792AR-etiquette-coeur-12-pcs.jpg",
            "https://www.fetez-moi.net/391321/792AR-etiquette-coeur-12-pcs.jpg",
            "https://www.fetez-moi.net/397759-thickbox_default/792AR-etiquette-coeur-12-pcs.jpg",
            "https://www.fetez-moi.net/397759/792AR-etiquette-coeur-12-pcs.jpg",
            "https://www.fetez-moi.net/395904-thickbox_default/792AR-etiquette-coeur-12-pcs.jpg",
            "https://www.fetez-moi.net/395904/792AR-etiquette-coeur-12-pcs.jpg"
        ]
    }
]